bayesian_bozo
