Metadata-Version: 1.1
Name: BayesianBozo
Version: 0.0.8
Summary: Bayesian statistical functions for Python
Home-page: https://github.com/jcbozonier/BayesianBozo
Author: Justin Bozonier
Author-email: darkxanthos@gmail.com
License: MIT
Keywords: bayes statistics probability inferrence
Platform: UNKNOWN
Classifier: Development Status :: 3 - Alpha
Classifier: Intended Audience :: Developers
Classifier: Topic :: Software Development :: Build Tools
Classifier: License :: OSI Approved :: MIT License
Classifier: Programming Language :: Python :: 2
Classifier: Programming Language :: Python :: 2.6
Classifier: Programming Language :: Python :: 2.7
Classifier: Programming Language :: Python :: 3
Classifier: Programming Language :: Python :: 3.2
Classifier: Programming Language :: Python :: 3.3
Classifier: Programming Language :: Python :: 3.4
